scuttle/__init__.py
scuttle/L1/__init__.py
scuttle/L1/adc.py
scuttle/L1/bmp.py
scuttle/L1/camera.py
scuttle/L1/encoder.py
scuttle/L1/gamepad.py
scuttle/L1/lidar.py
scuttle/L1/motors.py
scuttle/L1/mpu.py
scuttle/L1/rssi.py
scuttle/L1/servo.py
scuttle/L1/text2speech.py
scuttle/L2/__init__.py
scuttle/L2/color_target.py
scuttle/L2/heading.py
scuttle/L2/inverse_kinematics.py
scuttle/L2/kinematics.py
scuttle/L2/log.py
scuttle/L2/obstacle.py
scuttle/L2/speed_control.py
scuttle/L2/track_target.py
scuttle/L3/__init__.py
scuttle/L3/drive_mt.py
scuttle/L3/telemetry.py
scuttlepy-0.1.1.dist-info/METADATA
scuttlepy-0.1.1.dist-info/WHEEL
scuttlepy-0.1.1.dist-info/top_level.txt
scuttlepy-0.1.1.dist-info/RECORD
