Metadata-Version: 2.1
Name: scuttlepy
Version: 0.1.1
Summary: SCUTTLE Python Library
Home-page: https://github.com/ansarid/SCUTTLE
Author: Daniyal Ansari
Author-email: daniyal.s.ansari+pypi@gmail.com
License: GNU General Public License v3.0
Keywords: scuttle
Platform: UNKNOWN
